sopel_emotes/__init__.py
sopel_emotes/plugin.py
sopel_emotes-1.0.1.dist-info/COPYING
sopel_emotes-1.0.1.dist-info/METADATA
sopel_emotes-1.0.1.dist-info/WHEEL
sopel_emotes-1.0.1.dist-info/entry_points.txt
sopel_emotes-1.0.1.dist-info/top_level.txt
sopel_emotes-1.0.1.dist-info/RECORD
