Metadata-Version: 2.1
Name: sopel-emotes
Version: 1.0.1
Summary: Searches for emotes, denoted by `:emote_name:` from multiple sources (FFZ/BTTV/7TV) and links the associated image urls.
Author-email: Scott Adie <sopel-emotes@adie.io>
License: EFL-2.0
Project-URL: Homepage, https://github.com/sc0tt/sopel-emotes
Project-URL: Bug Tracker, https://github.com/sc0tt/sopel-emotes/issues
Keywords: sopel,plugin,bot,irc,twitch,emotes,7TV,BTTV,FFZ,FrankerFaceZ
Platform: Linux x86, x86-64
Classifier: Intended Audience :: Developers
Classifier: Intended Audience :: System Administrators
Classifier: License :: Eiffel Forum License (EFL)
Classifier: License :: OSI Approved :: Eiffel Forum License
Classifier: Topic :: Communications :: Chat :: Internet Relay Chat
Requires-Python: <4,>=3.8
License-File: COPYING
Requires-Dist: sopel>=8.0
Requires-Dist: requests
